boutpy/__init__.py
boutpy/bin/__init__.py
boutpy/bin/compare_inp.py
boutpy/bin/gamma.py
boutpy/bin/gamma_plot.py
boutpy/bin/growthrate.py
boutpy/bin/jobstate.py
boutpy/bin/jobsubmit.py
boutpy/bin/scan.py
boutpy/boutdata/__init__.py
boutpy/boutdata/boutgrid.py
boutpy/boutdata/collect.py
boutpy/boutdata/field.py
boutpy/boutdata/gen_surface.py
boutpy/boutdata/map_pfile2grid.py
boutpy/boutdata/mayavi2.py
boutpy/boutdata/pol_slice.py
boutpy/boutdata/restart.py
boutpy/boutdata/vector.py
boutpy/boututils/__init__.py
boutpy/boututils/calculus.py
boutpy/boututils/compare_inp.py
boutpy/boututils/contour.py
boutpy/boututils/datafile.py
boutpy/boututils/elmsize.py
boutpy/boututils/fileio.py
boutpy/boututils/functions.py
boutpy/boututils/getmpirun.py
boutpy/boututils/interp_smooth.py
boutpy/boututils/launch.py
boutpy/boututils/linear_regression.py
boutpy/boututils/ncpus.py
boutpy/boututils/pfile.py
boutpy/boututils/plotdata.py
boutpy/boututils/shell.py
boutpy/boututils/showdata.py
boutpy/boututils/spectrogram.py
boutpy/post_bout/ListDict.py
boutpy/post_bout/__init__.py
boutpy/post_bout/basic_info.py
boutpy/post_bout/pb_corral.py
boutpy/post_bout/pb_draw.py
boutpy/post_bout/pb_nonlinear.py
boutpy/post_bout/pb_present.py
boutpy/post_bout/read_cxx.py
boutpy/post_bout/read_inp.py
boutpy/visualization/__init__.py
boutpy/visualization/axes_zoom_effect.py
boutpy/visualization/plotconfig.py
boutpy/visualization/plotfigs.py
boutpy-0.0.1.dev3.data/scripts/compare_inp.py
boutpy-0.0.1.dev3.data/scripts/gamma.py
boutpy-0.0.1.dev3.data/scripts/growthrate.py
boutpy-0.0.1.dev3.data/scripts/jobstate.py
boutpy-0.0.1.dev3.data/scripts/jobsubmit.py
boutpy-0.0.1.dev3.data/scripts/scan.py
boutpy-0.0.1.dev3.dist-info/METADATA
boutpy-0.0.1.dev3.dist-info/RECORD
boutpy-0.0.1.dev3.dist-info/WHEEL
boutpy-0.0.1.dev3.dist-info/top_level.txt
