Metadata-Version: 2.1
Name: boutpy
Version: 0.0.1.dev3
Summary: Common python2.x toolkits for BOUT++ project
Home-page: https://gitlab.com/conderls/boutpy
Author: J.G. Chen, BOUT++ TEAM
Author-email: cjgls@pku.edu.cn
License: UNKNOWN
Project-URL: Source, https://gitlab.com/conderls/boutpy
Project-URL: Documentation, https://boutpy.readthedocs.io
Project-URL: Tracker, https://gitlab.com/conderls/boutpy/issues
Platform: UNKNOWN
Classifier: Programming Language :: Python :: 2.7
Classifier: License :: OSI Approved :: MIT License
Classifier: Operating System :: OS Independent
Requires-Python: ~=2.7
Requires-Dist: numpy (>=1.13.1)
Requires-Dist: scipy
Requires-Dist: matplotlib (>=2.0.2)
Requires-Dist: pandas (>=0.18.1)
Requires-Dist: ipython (>=5.5.0)
Requires-Dist: configobj
Requires-Dist: netCDF4
Requires-Dist: future
